pyelection
