Metadata-Version: 2.1
Name: pyelection
Version: 0.0.2
Summary: Obtain historical US presidential election data
Home-page: https://github.com/jkubo/pyelection
Author: Jay Kubo
Author-email: jaykubo@outlook.com
License: UNKNOWN
Platform: UNKNOWN
Classifier: Development Status :: 3 - Alpha
Classifier: License :: OSI Approved :: BSD License
Classifier: Programming Language :: Python
Provides: pyelection
